carbontrace/__init__.py
carbontrace/_modidx.py
carbontrace/network.py
carbontrace/trace.py
carbontrace-0.0.4.dist-info/LICENSE
carbontrace-0.0.4.dist-info/METADATA
carbontrace-0.0.4.dist-info/WHEEL
carbontrace-0.0.4.dist-info/entry_points.txt
carbontrace-0.0.4.dist-info/top_level.txt
carbontrace-0.0.4.dist-info/RECORD
